Verilog/teste/dijkstra1.v
module dijkstra(out, clk, reset);
	input clk, reset;
	output reg [32-1:0] out;
	integer i, v;

	//parameters
	reg [32-1:0]graph[512-1:0];
	reg [32-1:0]src, dest, u;
	reg signed [32-1:0]parent[32-1:0];

	//intern
	reg [32-1:0] dist[32-1:0], sptSet[32-1:0];
	reg [32-1:0] min = 9999999;
	//inicializacao provisoria
	initial begin
		for (i = 0; i < 32; i = i + 1) begin
			parent[i] = -1;
			dist[i] = 9999999;
			sptSet[i] = 0;
			graph[i] = 0;
		end
		src = 0;
		dest = 3;
		graph[0+9*1] = 1;
		graph[0+9*2] = 1;
		graph[1+9*3] = 4;
	end

	always @(posedge clk) begin
		dist[src] = 0;

		for (i = 0; i < 31; i = i + 1) begin
			//u = minDist(dist, sptSet)
			min = 9999999;
			for (v = 0; v < 32; v = v + 1) begin
				if(sptSet[v] == 0 && dist[v] <= min)begin
					min = dist[v];
					u = i;
				end
			end	
			//if(u != 0)begin
			//$write(u,"\n");end
			sptSet[u] = 1;
			for (v = 0; v < 31; v = v + 1) begin
				if (!sptSet[v] && graph[u+9*v] && dist[u] + graph[u+9*v] < dist[v]) begin
					parent[v] = u; 
					dist[v] = dist[u] + graph[u+9*v]; 
				end
			end
		end

		out = dist[dest];
		$write(out,"\n");
	end
endmodule


module test;
	reg clk;
	reg reset;
	initial begin
		$dumpfile("dij.vcd");
		$dumpvars;
		clk = 0;
		reset = 0;
		#30 $finish;
	end
	always #1 clk = !clk;
	wire [32-1:0] out;
	dijkstra d1 (out, clk, reset);
endmodule

Verilog/teste/dij.vcd
$date
	Thu Jul 16 13:37:49 2020
$end
$version
	Icarus Verilog
$end
$timescale
	1s
$end
$scope module test $end
$var wire 32 ! out [31:0] $end
$var reg 1 " clk $end
$var reg 1 # reset $end
$scope module d1 $end
$var wire 1 " clk $end
$var wire 1 # reset $end
$var reg 32 $ dest [31:0] $end
$var reg 32 % min [31:0] $end
$var reg 32 & out [31:0] $end
$var reg 32 ' src [31:0] $end
$var reg 32 ( u [31:0] $end
$var integer 32 ) i [31:0] $end
$var integer 32 * v [31:0] $end
$upscope $end
$upscope $end
$enddefinitions $end
#0
$dumpvars
bx *
b100000 )
bx (
b0 '
bx &
b100110001001011001111111 %
b11 $
0#
0"
bx !
$end
#1
b101 !
b101 &
b11110 (
b100110001001011001111111 %
b11111 *
b11111 )
1"
#2
0"
#3
b11110 (
b11111 *
b11111 )
1"
#4
0"
#5
b11110 (
b11111 *
b11111 )
1"
#6
0"
#7
b11110 (
b11111 *
b11111 )
1"
#8
0"
#9
b11110 (
b11111 *
b11111 )
1"
#10
0"
#11
b11110 (
b11111 *
b11111 )
1"
#12
0"
#13
b11110 (
b11111 *
b11111 )
1"
#14
0"
#15
b11110 (
b11111 *
b11111 )
1"
#16
0"
#17
b11110 (
b11111 *
b11111 )
1"
#18
0"
#19
b11110 (
b11111 *
b11111 )
1"
#20
0"
#21
b11110 (
b11111 *
b11111 )
1"
#22
0"
#23
b11110 (
b11111 *
b11111 )
1"
#24
0"
#25
b11110 (
b11111 *
b11111 )
1"
#26
0"
#27
b11110 (
b11111 *
b11111 )
1"
#28
0"
#29
b11110 (
b11111 *
b11111 )
1"
